{"status":"success","message":"Workout plan generated successfully","result":{"goal":"Cardio + circuit training","fitness_level":"Advanced","total_weeks":4,"schedule":{"days_per_week":4,"session_duration":60},"exercises":[{"day":"Monday","exercises":[{"name":"High-Intensity Interval Running","duration":"15 minutes","repetitions":null,"sets":null,"equipment":"Treadmill or outdoor running"},{"name":"Circuit: Bodyweight Squats","duration":"10 minutes","repetitions":"15 reps per set","sets":"3 sets","equipment":"None"},{"name":"Circuit: Push-Ups","duration":"10 minutes","repetitions":"20 reps per set","sets":"3 sets","equipment":"None"},{"name":"Circuit: Burpees","duration":"10 minutes","repetitions":"15 reps per set","sets":"3 sets","equipment":"None"}]},{"day":"Wednesday","exercises":[{"name":"Rowing Machine Sprints","duration":"15 minutes","repetitions":null,"sets":null,"equipment":"Rowing machine"},{"name":"Circuit: Lunges","duration":"10 minutes","repetitions":"12 reps per leg","sets":"3 sets","equipment":"None"},{"name":"Circuit: Plank to Push-Up","duration":"10 minutes","repetitions":"12 reps","sets":"3 sets","equipment":"None"},{"name":"Circuit: Mountain Climbers","duration":"10 minutes","repetitions":"20 reps per set","sets":"3 sets","equipment":"None"}]},{"day":"Friday","exercises":[{"name":"Cycling Sprints","duration":"15 minutes","repetitions":null,"sets":null,"equipment":"Stationary bike or outdoor cycling"},{"name":"Circuit: Jumping Lunges","duration":"10 minutes","repetitions":"12 reps per leg","sets":"3 sets","equipment":"None"},{"name":"Circuit: Bicycle Crunches","duration":"10 minutes","repetitions":"20 reps","sets":"3 sets","equipment":"None"},{"name":"Circuit: Russian Twists","duration":"10 minutes","repetitions":"15 reps per side","sets":"3 sets","equipment":"None, optionally with weight"}]},{"day":"Sunday","exercises":[{"name":"Stair Running or Step-Ups","duration":"15 minutes","repetitions":null,"sets":null,"equipment":"Stairs or step platform"},{"name":"Circuit: Jump Rope","duration":"10 minutes","repetitions":"Continuous","sets":"3 sets","equipment":"Jump rope"},{"name":"Circuit: Sit-Ups and Leg Raises","duration":"10 minutes","repetitions":"15 reps each","sets":"3 sets","equipment":"None"},{"name":"Cooldown & Stretching","duration":"10 minutes","repetitions":null,"sets":null,"equipment":"None"}]}],"seo_title":"Advanced 4-Week Cardio & Circuit Training Workout Plan","seo_content":"Boost your fitness with this advanced 4-week cardio and circuit training plan. Designed for experienced individuals, it combines high-intensity cardio sessions with effective circuit exercises to improve endurance, strength, and overall fitness. Perfect for those aiming to challenge themselves and achieve their fitness goals.","seo_keywords":"advanced workout plan, cardio circuit training, 4-week fitness plan, high-intensity exercise"},"cacheTime":1777372504075}