{"result":{"goal":"Upper/Lower split + cardio","fitness_level":"beginner","total_weeks":4,"schedule":{"days_per_week":4,"session_duration":60},"exercises":[{"day":"Monday","exercises":[{"name":"Bodyweight Squats","duration":"5 minutes","repetitions":"12-15 reps","sets":"3","equipment":"None"},{"name":"Push-Ups (Modified if needed)","duration":"5 minutes","repetitions":"10-12 reps","sets":"3","equipment":"None"},{"name":"Walking or Jogging (Outdoor or Treadmill)","duration":"20 minutes","repetitions":"N/A","sets":"N/A","equipment":"None or Treadmill"},{"name":"Plank","duration":"3 minutes","repetitions":"Hold for 30 seconds each","sets":"3","equipment":"None"}]},{"day":"Tuesday","exercises":[{"name":"Rest or Light Activity (e.g., stretching, walking)","duration":"60 minutes","repetitions":"N/A","sets":"N/A","equipment":"None"}]},{"day":"Wednesday","exercises":[{"name":"Dumbbell Deadlifts (Light weight)","duration":"5 minutes","repetitions":"12 reps","sets":"3","equipment":"Dumbbells"},{"name":"Dumbbell Shoulder Press","duration":"5 minutes","repetitions":"12 reps","sets":"3","equipment":"Dumbbells"},{"name":"Stationary Cycling or brisk walking","duration":"20 minutes","repetitions":"N/A","sets":"N/A","equipment":"Stationary Bike or outdoors"},{"name":"Bird Dog","duration":"5 minutes","repetitions":"10 reps per side","sets":"3","equipment":"None"}]},{"day":"Thursday","exercises":[{"name":"Rest or Light Activity (e.g., stretching, walking)","duration":"60 minutes","repetitions":"N/A","sets":"N/A","equipment":"None"}]}],"seo_title":"Beginner Upper/Lower Split Workout Plan with Cardio - 4 Weeks","seo_content":"Start your fitness journey with this beginner-friendly 4-week workout plan focusing on upper/lower body split combined with cardio. Designed to build strength and endurance gradually, this plan is ideal for newcomers looking to improve overall fitness with 4 sessions per week. Each session lasts around 60 minutes, including warm-up, workout, and cool-down. Suitable exercises require minimal equipment, making it easy to perform at home or in the gym.","seo_keywords":"beginner workout plan, upper lower split, cardio for beginners, 4 week fitness plan, home workout"},"cacheTime":1776086034091,"time":1777086752149,"status":"success","message":"Data retrieved from cache"}